copy.py
setup.py
micropython_copy.egg-info/PKG-INFO
micropython_copy.egg-info/SOURCES.txt
micropython_copy.egg-info/dependency_links.txt
micropython_copy.egg-info/requires.txt
micropython_copy.egg-info/top_level.txt