Metadata-Version: 1.0
Name: micropython-copy
Version: 0.0.2
Summary: CPython copy module ported to MicroPython
Home-page: https://github.com/micropython/micropython/issues/405
Author: MicroPython Developers
Author-email: micro-python@googlegroups.com
License: Python
Platform: UNKNOWN
